<?xml version="1.0" encoding="utf-8"?>
<cycom>
    <record id="ir_cron_employee_document_expiry_hr" model="ir.cron">
        <field name="name">Employee documents: notify HR Managers when expired</field>
        <field name="model_id" ref="hr.model_hr_employee"/>
        <field name="state">code</field>
        <field name="code">model._cron_notify_document_expiry_to_hr()</field>
        <field name="interval_number">1</field>
        <field name="interval_type">days</field>
    </record>
</cycom>
